{
	"threads": 1,
	"url": "http://activedata.allizom.org/query",
	"constants":{
		"pyLibrary.env.http.default_headers":{
			"referer": "https://wiki.mozilla.org/Auto-tools/Projects/ActiveData"
		}
	},
	"source": {
		"host": "http://activedata.allizom.org",
		"port": 9200,
		"index": "coverage",
		"type": "code_coverage",
		"debug": false
	},
	"destination":{
		"host": "http://activedata.allizom.org",
		"port": 9200,
		"index": "coverage-summary",
		"type": "code_coverage",
		"schema": {"$ref": "../schema/coverage.json"},
		"debug": false
	},
	"debug": {
		"trace": true,
		"cprofile": false,
		"log": [
			{
				"log_type": "console"
			},
			{
				"class": "logging.handlers.RotatingFileHandler",
				"filename": "/logs/codecoverage.log",
				"maxBytes": 10000000,
				"backupCount": 10,
				"encoding": "utf8"
			},
			{
				"log_type": "ses",
				"from_address": "klahnakoski@mozilla.com",
				"to_address": "klahnakoski@mozilla.com",
				"subject": "[ALERT][Manager] Problem in CodeCoverage Post Processing",
				"$ref": "file://~/private.json#aws_credentials"
			}
		]
	}
}
